desktop.ini
LiquPy-0.13.1.dist-info/DESCRIPTION.rst
LiquPy-0.13.1.dist-info/METADATA
LiquPy-0.13.1.dist-info/RECORD
LiquPy-0.13.1.dist-info/WHEEL
LiquPy-0.13.1.dist-info/desktop.ini
LiquPy-0.13.1.dist-info/metadata.json
LiquPy-0.13.1.dist-info/top_level.txt
liqupy/__init__.py
liqupy/boreholes.py
liqupy/desktop.ini
liqupy/points.py
liqupy/default_datasets/__init__.py
liqupy/default_datasets/base.py
